reader/__init__.py
reader/__main__.py
reader/config.toml
reader/feed.py
reader/viewer.py
realpython_reader_fancyerii_flit-1.1.2.dist-info/entry_points.txt
realpython_reader_fancyerii_flit-1.1.2.dist-info/LICENSE
realpython_reader_fancyerii_flit-1.1.2.dist-info/WHEEL
realpython_reader_fancyerii_flit-1.1.2.dist-info/METADATA
realpython_reader_fancyerii_flit-1.1.2.dist-info/RECORD
