Metadata-Version: 2.1
Name: realpython-reader-fancyerii-flit
Version: 1.1.2
Summary: Real Python feed reader.
Author-email: lili <fancyerii@gmail.com>
Classifier: License :: OSI Approved :: MIT License
Classifier: Programming Language :: Python :: 3
Project-URL: Home, https://github.com/realpython/reader
